pudim_hunter_driver_simply_hired/__init__.py
pudim_hunter_driver_simply_hired/_version.py
pudim_hunter_driver_simply_hired/driver.py
pudim_hunter_driver_simply_hired-1.0.1.dist-info/LICENSE.md
pudim_hunter_driver_simply_hired-1.0.1.dist-info/METADATA
pudim_hunter_driver_simply_hired-1.0.1.dist-info/WHEEL
pudim_hunter_driver_simply_hired-1.0.1.dist-info/top_level.txt
pudim_hunter_driver_simply_hired-1.0.1.dist-info/RECORD
