Metadata-Version: 2.1
Name: pudim-hunter-driver-simply-hired
Version: 1.0.1
Summary: Simply Hired driver implementation for The Pudim Hunter platform
Author-email: The Pudim Hunter Team <luis.reis@gmail.com>
License: MIT
Project-URL: Source, https://github.com/luismr/pudim-hunter-driver-simply-hired
Project-URL: Bug Tracker, https://github.com/luismr/pudim-hunter-driver-simply-hired/issues
Classifier: Development Status :: 3 - Alpha
Classifier: Intended Audience :: Developers
Classifier: Operating System :: OS Independent
Classifier: Programming Language :: Python :: 3
Classifier: Programming Language :: Python :: 3.9
Classifier: Topic :: Software Development :: Libraries :: Python Modules
Requires-Python: >=3.9
License-File: LICENSE.md
Requires-Dist: pudim-hunter-driver-scraper==1.0.1
Requires-Dist: setuptools>=61.0.0
Requires-Dist: pytest==7.4.3
Requires-Dist: pytest-mock==3.12.0
Requires-Dist: python-dotenv==1.0.0
Requires-Dist: requests==2.31.0
Requires-Dist: setuptools-scm==8.0.0
